{"uuid":"recommended421670","createDate":1468690500000,"customConfigJson":"{\"gameId\":\"421670\",\"readError\":\"false\",\"syncTime\":\"2024-04-30 17:04:23\",\"ratingSummary\":\"推荐\",\"postTime\":\"2016-07-17\",\"gameName\":\"CUPID - A free to play Visual Novel\",\"gameLink\":\"https://store.steampowered.com/app/421670\",\"recommendedLink\":\"https://steamcommunity.com/id/oneness629/recommended/421670/\",\"playTime\":\"3.5\",\"updateTime\":\"2016-07-17\",\"reviewPlayTime\":\"3.5\",\"communityLink\":\"https://steamcommunity.com/app/421670\"}","type":"steamReview","title":"评测 > CUPID - A free to play Visual Novel","content":"<div id=\"ReviewText\">\n 游戏的音乐相当不错~ 特别是标题的那首，可惜游戏没有ost~\n <br>\n 没有人物对话语言，\n <br>\n 但是有双语汉化，汉化是另外一个牛人花2周时间搞的~腻害啊~\n <br>\n <br>\n 剧情前期还是不错的~后期的剧情好阴暗，其实不是很懂这剧情~\n <br>\n 游戏有多个结局，我暂时只打出2个~~\n <br>\n <br>\n 成就竟然有60多个~可怕~看来剧情还有很多深奥的东西，可惜不想继续挖了~\n <br>\n <br>\n 总体来说是个不错的游戏\n <br>\n ~剧情压抑~\n</div>\n<div id=\"ReviewEdit\" style=\"display: none\">\n <textarea id=\"ReviewEditTextArea\" class=\"review_edit_text_area\" maxlength=\"8000\" rows=\"2\" cols=\"80\">游戏的音乐相当不错~ 特别是标题的那首，可惜游戏没有ost~\n没有人物对话语言，\n但是有双语汉化，汉化是另外一个牛人花2周时间搞的~腻害啊~\n\n剧情前期还是不错的~后期的剧情好阴暗，其实不是很懂这剧情~\n游戏有多个结局，我暂时只打出2个~~\n\n成就竟然有60多个~可怕~看来剧情还有很多深奥的东西，可惜不想继续挖了~\n\n总体来说是个不错的游戏\n~剧情压抑~</textarea>\n <div class=\"review_edit_received_compensation\">\n  <input type=\"checkbox\" id=\"ReceivedCompensationCheckbox\" value=\"1\"> <label for=\"ReceivedCompensationCheckbox\">如果您是免费获取的此产品，请勾选此框 <a data-tooltip-text=\"如果您是免费获取的此产品，请勾选此框。您的评测旁会显示“免费获取的产品”。如果您评测此游戏还收到了其他报酬，必须在您的评测文本中披露。\">(?)</a></label>\n </div>\n <div style=\"float: left\">\n  您推荐这款游戏吗？ <span class=\"btnv6_blue_hoverfade btn_small_thin ico_hover active\" onclick=\"SetOwnerRatingPositive();\" id=\"OwnerVoteUpBtn\"> <span><i class=\"ico16 thumb_up\"></i> 是</span> </span> <span class=\"btnv6_blue_hoverfade btn_small_thin ico_hover \" onclick=\"SetOwnerRatingNegative();\" id=\"OwnerVoteDownBtn\"> <span><i class=\"ico16 thumb_down\"></i>否</span> </span>\n </div>\n <div style=\"float: right\">\n  <span class=\"btn_small_thin btn_grey_white_innerfade\" onclick=\"CancelEdits();\" id=\"CancelEditsBtn\"> <span>取消</span> </span> <span class=\"btn_small_thin btn_blue_white_innerfade\" onclick=\"SaveReview();\" id=\"SaveReviewBtn\"> <span>保存修改</span> </span>\n </div>\n <div style=\"clear: both\"></div>\n</div>","bgArchivesType":{"uuid":"d612b8f8-70ee-4b73-9f32-04475fbe954e","code":"Steam游戏评测","name":"Steam游戏评测","parentUuid":"a4fb2b94-3d2b-414d-8745-49677c3c7d22"}}