{"uuid":"recommended373670","createDate":1760410037424,"customConfigJson":"{\"gameId\":\"373670\",\"readError\":\"false\",\"syncTime\":\"2024-04-30 12:24:01\",\"ratingSummary\":\"推荐\",\"postTime\":\"2019-07-09\",\"gameName\":\"Arkhelom 3D\",\"gameLink\":\"https://store.steampowered.com/app/373670\",\"recommendedLink\":\"https://steamcommunity.com/id/oneness629/recommended/373670/\",\"playTime\":\"0.1\",\"updateTime\":\"2019-07-09\",\"reviewPlayTime\":\"0.1\",\"communityLink\":\"https://steamcommunity.com/app/373670\"}","type":"steamReview","title":"评测 > Arkhelom 3D","content":"<div id=\"ReviewText\">\n ~一个非常复古也非常低分辨率的3D打飞机游戏~\n <br>\n 游戏需要使用兼容模式进行，不然会提示unable to set graphics mode\n <br>\n 游戏有24个关卡，通过鼠标无缝移动（鼠标有多快，飞船就有多块~）\n <br>\n 游戏中的火焰武器很神奇，玩家移动后，射出去的火焰也会随着玩家一起移动~\n <br>\n ~界面关卡爆炸特效绝对是90年代的效果~也不支持steam内置界面~\n <br>\n <br>\n ~画面比较粗糙~游戏还是可以的~但不推荐买~\n</div>\n<div id=\"ReviewEdit\" style=\"display: none\">\n <textarea id=\"ReviewEditTextArea\" class=\"review_edit_text_area\" maxlength=\"8000\" rows=\"2\" cols=\"80\">~一个非常复古也非常低分辨率的3D打飞机游戏~\n游戏需要使用兼容模式进行，不然会提示unable to set graphics mode\n游戏有24个关卡，通过鼠标无缝移动（鼠标有多快，飞船就有多块~）\n游戏中的火焰武器很神奇，玩家移动后，射出去的火焰也会随着玩家一起移动~\n~界面关卡爆炸特效绝对是90年代的效果~也不支持steam内置界面~\n\n~画面比较粗糙~游戏还是可以的~但不推荐买~</textarea>\n <div class=\"review_edit_received_compensation\">\n  <input type=\"checkbox\" id=\"ReceivedCompensationCheckbox\" value=\"1\"> <label for=\"ReceivedCompensationCheckbox\">如果您是免费获取的此产品，请勾选此框 <a data-tooltip-text=\"如果您是免费获取的此产品，请勾选此框。您的评测旁会显示“免费获取的产品”。如果您评测此游戏还收到了其他报酬，必须在您的评测文本中披露。\">(?)</a></label>\n </div>\n <div style=\"float: left\">\n  您推荐这款游戏吗？ <span class=\"btnv6_blue_hoverfade btn_small_thin ico_hover active\" onclick=\"SetOwnerRatingPositive();\" id=\"OwnerVoteUpBtn\"> <span><i class=\"ico16 thumb_up\"></i> 是</span> </span> <span class=\"btnv6_blue_hoverfade btn_small_thin ico_hover \" onclick=\"SetOwnerRatingNegative();\" id=\"OwnerVoteDownBtn\"> <span><i class=\"ico16 thumb_down\"></i>否</span> </span>\n </div>\n <div style=\"float: right\">\n  <span class=\"btn_small_thin btn_grey_white_innerfade\" onclick=\"CancelEdits();\" id=\"CancelEditsBtn\"> <span>取消</span> </span> <span class=\"btn_small_thin btn_blue_white_innerfade\" onclick=\"SaveReview();\" id=\"SaveReviewBtn\"> <span>保存修改</span> </span>\n </div>\n <div style=\"clear: both\"></div>\n</div>","bgArchivesType":{"uuid":"d612b8f8-70ee-4b73-9f32-04475fbe954e","code":"Steam游戏评测","name":"Steam游戏评测","parentUuid":"a4fb2b94-3d2b-414d-8745-49677c3c7d22"}}