{"uuid":"recommended1117140","createDate":1760410020441,"customConfigJson":"{\"gameId\":\"1117140\",\"readError\":\"false\",\"syncTime\":\"2024-04-30 12:23:38\",\"ratingSummary\":\"推荐\",\"postTime\":\"2019-08-02\",\"gameName\":\"Euro Truck Simulator 2 - Goodyear Tyres Pack\",\"gameLink\":\"https://store.steampowered.com/app/1117140\",\"recommendedLink\":\"https://steamcommunity.com/id/oneness629/recommended/1117140/\",\"playTime\":\"0.0\",\"updateTime\":\"2019-08-02\",\"reviewPlayTime\":\"0.0\",\"communityLink\":\"https://steamcommunity.com/app/1117140\"}","type":"steamReview","title":"评测 > Euro Truck Simulator 2 - Goodyear Tyres Pack","content":"<div id=\"ReviewText\">\n ~欧卡2 好年/固特异包~ \n <br>\n ~完成好年&amp;固特异限时线上任务，免费得DLC~非常划算~还有一个steam物品（车内装饰）~\n <br>\n <br>\n ~前提是要有法国、波罗的海彼岸、意大利、斯堪的纳维亚地图之一才会在线上刷出固特异任务~\n <br>\n ~果然之前夏促最后一天补齐地图DLC还是有点用的~\n <br>\n <br>\n ~10个运载固特异轮胎任务~不限制路线长度和地区~只限制货物~\n <br>\n ~固特异拖车不支持高级拖车，要去设置里取消~\n <br><a class=\"bb_link\" href=\"https://steamcommunity.com/sharedfiles/filedetails/?id=1822759393\" target=\"_blank\" rel=\"\" id=\"dynamiclink_0\">https://steamcommunity.com/sharedfiles/filedetails/?id=1822759393</a>\n <br><a class=\"bb_link\" href=\"https://steamcommunity.com/sharedfiles/filedetails/?id=1821823825\" target=\"_blank\" rel=\"\" id=\"dynamiclink_1\">https://steamcommunity.com/sharedfiles/filedetails/?id=1821823825</a>\n <br>\n <br>\n</div>\n<div id=\"ReviewEdit\" style=\"display: none\">\n <textarea id=\"ReviewEditTextArea\" class=\"review_edit_text_area\" maxlength=\"8000\" rows=\"2\" cols=\"80\">~欧卡2 好年/固特异包~ \n~完成好年&amp;固特异限时线上任务，免费得DLC~非常划算~还有一个steam物品（车内装饰）~\n\n~前提是要有法国、波罗的海彼岸、意大利、斯堪的纳维亚地图之一才会在线上刷出固特异任务~\n~果然之前夏促最后一天补齐地图DLC还是有点用的~\n\n~10个运载固特异轮胎任务~不限制路线长度和地区~只限制货物~\n~固特异拖车不支持高级拖车，要去设置里取消~\nhttps://steamcommunity.com/sharedfiles/filedetails/?id=1822759393\nhttps://steamcommunity.com/sharedfiles/filedetails/?id=1821823825\n\n</textarea>\n <div class=\"review_edit_received_compensation\">\n  <input type=\"checkbox\" id=\"ReceivedCompensationCheckbox\" value=\"1\"> <label for=\"ReceivedCompensationCheckbox\">如果您是免费获取的此产品，请勾选此框 <a data-tooltip-text=\"如果您是免费获取的此产品，请勾选此框。您的评测旁会显示“免费获取的产品”。如果您评测此游戏还收到了其他报酬，必须在您的评测文本中披露。\">(?)</a></label>\n </div>\n <div style=\"float: left\">\n  您推荐这款游戏吗？ <span class=\"btnv6_blue_hoverfade btn_small_thin ico_hover active\" onclick=\"SetOwnerRatingPositive();\" id=\"OwnerVoteUpBtn\"> <span><i class=\"ico16 thumb_up\"></i> 是</span> </span> <span class=\"btnv6_blue_hoverfade btn_small_thin ico_hover \" onclick=\"SetOwnerRatingNegative();\" id=\"OwnerVoteDownBtn\"> <span><i class=\"ico16 thumb_down\"></i>否</span> </span>\n </div>\n <div style=\"float: right\">\n  <span class=\"btn_small_thin btn_grey_white_innerfade\" onclick=\"CancelEdits();\" id=\"CancelEditsBtn\"> <span>取消</span> </span> <span class=\"btn_small_thin btn_blue_white_innerfade\" onclick=\"SaveReview();\" id=\"SaveReviewBtn\"> <span>保存修改</span> </span>\n </div>\n <div style=\"clear: both\"></div>\n</div>","bgArchivesType":{"uuid":"d612b8f8-70ee-4b73-9f32-04475fbe954e","code":"Steam游戏评测","name":"Steam游戏评测","parentUuid":"a4fb2b94-3d2b-414d-8745-49677c3c7d22"}}